octavus_cli/__init__.py
octavus_cli-0.0.1.dist-info/METADATA
octavus_cli-0.0.1.dist-info/WHEEL
octavus_cli-0.0.1.dist-info/licenses/LICENSE
octavus_cli-0.0.1.dist-info/RECORD
