Metadata-Version: 2.4
Name: octavus-cli
Version: 0.0.1
Summary: CLI for validating and syncing Octavus agent definitions
Author-email: Octavus AI <dev@octavus.ai>
License-Expression: MIT
License-File: LICENSE
Keywords: agents,ai,cli,octavus,sync,validate
Classifier: Development Status :: 1 - Planning
Classifier: Intended Audience :: Developers
Classifier: License :: OSI Approved :: MIT License
Classifier: Programming Language :: Python :: 3
Classifier: Programming Language :: Python :: 3.9
Classifier: Programming Language :: Python :: 3.10
Classifier: Programming Language :: Python :: 3.11
Classifier: Programming Language :: Python :: 3.12
Requires-Python: >=3.9
